yamlify/__init__.py
yamlify/convert.py
yamlify/data.py
yamlify/main.py
yamlify/template_renderer.py
yamlify/utils.py
yamlify/yaml_loader.py
yamlify_me-0.2.1.dist-info/licenses/LICENSE
yamlify_me-0.2.1.dist-info/METADATA
yamlify_me-0.2.1.dist-info/WHEEL
yamlify_me-0.2.1.dist-info/entry_points.txt
yamlify_me-0.2.1.dist-info/top_level.txt
yamlify_me-0.2.1.dist-info/RECORD
