Metadata-Version: 2.4
Name: yamlify-me
Version: 0.2.1
Summary: Yamlify Me is a document generation tool and python library, which combines yaml and Jinja2.
Author-email: Jens Klimke <jens.klimke@rwth-aachen.de>
License-Expression: MIT
Project-URL: Homepage, https://github.com/JensKlimke/yamlify
Project-URL: Issues, https://github.com/JensKlimke/yamlify/issues
Classifier: Development Status :: 4 - Beta
Classifier: Programming Language :: Python :: 3
Classifier: Programming Language :: Python :: 3.7
Classifier: Programming Language :: Python :: 3.8
Classifier: Programming Language :: Python :: 3.9
Classifier: Programming Language :: Python :: 3.10
Classifier: Operating System :: OS Independent
Classifier: Intended Audience :: Developers
Classifier: Topic :: Software Development :: Libraries :: Python Modules
Classifier: Topic :: Text Processing :: Markup
License-File: LICENSE
Requires-Dist: PyYAML>=6.0
Requires-Dist: Markdown>=3.0
Requires-Dist: Jinja2>=3.0
Provides-Extra: dev
Requires-Dist: pytest; extra == "dev"
Dynamic: license-file
